stat386_finalproject_divorce_crime/__init__.py
stat386_finalproject_divorce_crime/analysis.py
stat386_finalproject_divorce_crime/app.py
stat386_finalproject_divorce_crime/clean_data.py
stat386_finalproject_divorce_crime/wrangling.py
stat386_finalproject_divorce_crime-0.1.5.dist-info/licenses/LICENSE
stat386_finalproject_divorce_crime-0.1.5.dist-info/METADATA
stat386_finalproject_divorce_crime-0.1.5.dist-info/WHEEL
stat386_finalproject_divorce_crime-0.1.5.dist-info/entry_points.txt
stat386_finalproject_divorce_crime-0.1.5.dist-info/top_level.txt
stat386_finalproject_divorce_crime-0.1.5.dist-info/RECORD
